datasette_test_plugin.py
datasette_test_plugin-0.1.dist-info/LICENSE
datasette_test_plugin-0.1.dist-info/METADATA
datasette_test_plugin-0.1.dist-info/WHEEL
datasette_test_plugin-0.1.dist-info/entry_points.txt
datasette_test_plugin-0.1.dist-info/top_level.txt
datasette_test_plugin-0.1.dist-info/RECORD
