Metadata-Version: 2.1
Name: datasette-test-plugin
Version: 0.1
Summary: Part of datasette-test
Author: Simon Willison
License: Apache-2.0
Project-URL: Homepage, https://github.com/datasette/datasette-test-plugin
Project-URL: Changelog, https://github.com/datasette/datasette-test-plugin/releases
Project-URL: Issues, https://github.com/datasette/datasette-test-plugin/issues
Project-URL: CI, https://github.com/datasette/datasette-test-plugin/actions
Classifier: Framework :: Datasette
Classifier: License :: OSI Approved :: Apache Software License
Requires-Python: >=3.8
License-File: LICENSE
Requires-Dist: datasette
Provides-Extra: test
Requires-Dist: pytest ; extra == 'test'
Requires-Dist: pytest-asyncio ; extra == 'test'
